meeseeql/__init__.py
meeseeql/database_manager.py
meeseeql/main.py
meeseeql/password_provider.py
meeseeql/sql_transformer.py
meeseeql/tools/__init__.py
meeseeql/tools/execute_query.py
meeseeql/tools/reload_config.py
meeseeql/tools/search.py
meeseeql/tools/show_database_config.py
meeseeql/tools/sql_utils.py
meeseeql/tools/table_summary.py
meeseeql/tools/test_connection.py
meeseeql/tools/sql/mssql/columns.sql
meeseeql/tools/sql/mssql/enum_values.sql
meeseeql/tools/sql/mssql/foreign_key.sql
meeseeql/tools/sql/mssql/primary_key.sql
meeseeql/tools/sql/mssql/search.sql
meeseeql/tools/sql/mssql/table_exists.sql
meeseeql/tools/sql/mysql/columns.sql
meeseeql/tools/sql/mysql/enum_values.sql
meeseeql/tools/sql/mysql/foreign_key.sql
meeseeql/tools/sql/mysql/primary_key.sql
meeseeql/tools/sql/mysql/search.sql
meeseeql/tools/sql/mysql/table_exists.sql
meeseeql/tools/sql/postgresql/columns.sql
meeseeql/tools/sql/postgresql/enum_values.sql
meeseeql/tools/sql/postgresql/foreign_key.sql
meeseeql/tools/sql/postgresql/primary_key.sql
meeseeql/tools/sql/postgresql/search.sql
meeseeql/tools/sql/postgresql/table_exists.sql
meeseeql/tools/sql/snowflake/columns.sql
meeseeql/tools/sql/snowflake/enum_values.sql
meeseeql/tools/sql/snowflake/foreign_key.sql
meeseeql/tools/sql/snowflake/primary_key.sql
meeseeql/tools/sql/snowflake/search.sql
meeseeql/tools/sql/snowflake/table_exists.sql
meeseeql/tools/sql/sqlite/columns.sql
meeseeql/tools/sql/sqlite/enum_values.sql
meeseeql/tools/sql/sqlite/foreign_key.sql
meeseeql/tools/sql/sqlite/primary_key.sql
meeseeql/tools/sql/sqlite/search.sql
meeseeql/tools/sql/sqlite/table_exists.sql
meeseeql-1.1.1.dist-info/METADATA
meeseeql-1.1.1.dist-info/WHEEL
meeseeql-1.1.1.dist-info/entry_points.txt
meeseeql-1.1.1.dist-info/licenses/LICENSE
meeseeql-1.1.1.dist-info/RECORD
