Metadata-Version: 2.4
Name: meeseeql
Version: 1.1.1
Summary: A FastMCP server for exploring SQL databases
Author-email: Thomas Smith <thomas@apolloagriculture.com>
License: MIT
License-File: LICENSE
Keywords: database,fastmcp,mcp,mysql,postgresql,sql,sqlite
Classifier: Development Status :: 4 - Beta
Classifier: Intended Audience :: Developers
Classifier: License :: OSI Approved :: MIT License
Classifier: Programming Language :: Python :: 3
Classifier: Topic :: Database
Classifier: Topic :: Software Development :: Libraries :: Python Modules
Requires-Python: <3.14,>=3.11
Requires-Dist: aiomysql>=0.2.0
Requires-Dist: aiosqlite>=0.19.0
Requires-Dist: asyncpg>=0.28.0
Requires-Dist: fastmcp>=2.10.5
Requires-Dist: greenlet>=3.0.0
Requires-Dist: psycopg2-binary>=2.9.0
Requires-Dist: pydantic>=2.0.0
Requires-Dist: pymysql>=1.1.0
Requires-Dist: pyodbc>=4.0.39
Requires-Dist: pyyaml>=6.0
Requires-Dist: snowflake-sqlalchemy>=1.4.0
Requires-Dist: sqlalchemy>=2.0.0
Requires-Dist: sqlglot[rs]>=25.0.0
